[
    {
        "title": "Cosmology and Dark Matter",
        "thumbnail_url": "http://www.e-booksdirectory.com/images/12427.jpg",
        "author": "V. A. Rubakov",
        "publisher": "arXiv",
        "date_published": "2019",
        "number_of_page": "76",
        "isbn/asin": "",
        "download_link": "https://arxiv.org/abs/1912.04727"
    },
    {
        "title": "The PHP Programming Language",
        "thumbnail_url": "http://www.e-booksdirectory.com/images/12426.jpg",
        "author": "",
        "publisher": "CodeAhoy",
        "date_published": "2023",
        "number_of_page": "223",
        "isbn/asin": "",
        "download_link": ""
    },
    {
        "title": "Precalculus: An Inquiry-Based Approach",
        "thumbnail_url": "",
        "author": "William Mahavier, Paul Howard",
        "publisher": "Oklahoma Christian University",
        "date_published": "2023",
        "number_of_page": "152",
        "isbn/asin": "",
        "download_link": "https://www.ams.org/open-math-notes/omn-view-listing?listingId=111361"
    },
    {
        "title": "Photography in the Third Reich",
        "thumbnail_url": "http://www.e-booksdirectory.com/images/12424.jpg",
        "author": "Christopher Webster",
        "publisher": "Open Book Publishers",
        "date_published": "2021",
        "number_of_page": "312",
        "isbn/asin": "9781783749164",
        "download_link": "https://doi.org/10.11647/OBP.0202"
    },
    {
        "title": "Science, Evolution, and Creationism",
        "thumbnail_url": "http://www.e-booksdirectory.com/images/12423.jpg",
        "author": "",
        "publisher": "The National Academies Press",
        "date_published": "2008",
        "number_of_page": "88",
        "isbn/asin": "9780309131933",
        "download_link": "https://doi.org/10.17226/11876"
    },
    {
        "title": "Learning from Arguments: An Introduction to Philosophy",
        "thumbnail_url": "http://www.e-booksdirectory.com/images/12422.jpg",
        "author": "Daniel Z. Korman",
        "publisher": "PhilPapers Foundation",
        "date_published": "2022",
        "number_of_page": "248",
        "isbn/asin": "",
        "download_link": "https://open.umn.edu/opentextbooks/textbooks/learning-from-arguments-an-introduction-to-philosophy"
    },
    {
        "title": "Introduction to Engineering Thermodynamics",
        "thumbnail_url": "http://www.e-booksdirectory.com/images/12421.jpg",
        "author": "Claire Yu Yan",
        "publisher": "BCcampus",
        "date_published": "2022",
        "number_of_page": "430",
        "isbn/asin": "",
        "download_link": "https://open.umn.edu/opentextbooks/textbooks/introduction-to-engineering-thermodynamics"
    },
    {
        "title": "Twice in Time",
        "thumbnail_url": "http://www.e-booksdirectory.com/images/12420.jpg",
        "author": "Manly Wade Wellman",
        "publisher": "Galaxy Publishing Corp.",
        "date_published": "1958",
        "number_of_page": "190",
        "isbn/asin": "",
        "download_link": "https://archive.org/details/galaxy_novel_number_34_twice_in_time"
    },
    {
        "title": "Transformations of Surfaces",
        "thumbnail_url": "http://www.e-booksdirectory.com/images/12419.jpg",
        "author": "Luther Pfahler Eisenhart",
        "publisher": "Princeton University Press",
        "date_published": "1923",
        "number_of_page": "371",
        "isbn/asin": "",
        "download_link": "https://archive.org/download/transformationso00eiseuoft/transformationso00eiseuoft.pdf"
    },
    {
        "title": "Computer Networks From Scratch",
        "thumbnail_url": "http://www.e-booksdirectory.com/images/12418.jpg",
        "author": "Seth Archer Brown",
        "publisher": "",
        "date_published": "2022",
        "number_of_page": "",
        "isbn/asin": "",
        "download_link": ""
    },
    {
        "title": "Statistical Mechanics of Lattice Systems",
        "thumbnail_url": "http://www.e-booksdirectory.com/images/12417.jpg",
        "author": "Sacha Friedli, Yvan Velenik",
        "publisher": "Cambridge University Press",
        "date_published": "2017",
        "number_of_page": "590",
        "isbn/asin": "9781107184824",
        "download_link": "https://www.unige.ch/math/folks/velenik/smbook/"
    },
    {
        "title": "Phantom Duel",
        "thumbnail_url": "http://www.e-booksdirectory.com/images/12416.jpg",
        "author": "Ford McCormack",
        "publisher": "Infinity Science Fiction",
        "date_published": "1955",
        "number_of_page": "59",
        "isbn/asin": "",
        "download_link": "https://www.gutenberg.org/ebooks/67392"
    },
    {
        "title": "Semiconductors and Transistors",
        "thumbnail_url": "http://www.e-booksdirectory.com/images/12415.jpg",
        "author": "Alexander Schure",
        "publisher": "J. F. Rider",
        "date_published": "1951",
        "number_of_page": "145",
        "isbn/asin": "",
        "download_link": "https://worldradiohistory.com/BOOKSHELF-ARH/Rider-Books/Semiconductors%20and%20Transistors%20-%20Alexander%20Schure.pdf"
    },
    {
        "title": "Mathematics and Computation",
        "thumbnail_url": "http://www.e-booksdirectory.com/images/12414.jpg",
        "author": "Avi Wigderson",
        "publisher": "Princeton University Press",
        "date_published": "2019",
        "number_of_page": "340",
        "isbn/asin": "9780691189130",
        "download_link": "https://www.math.ias.edu/avi/book"
    },
    {
        "title": "Scala Book",
        "thumbnail_url": "http://www.e-booksdirectory.com/images/12413.jpg",
        "author": "Alvin Alexander",
        "publisher": "AlvinAlexander.com",
        "date_published": "2020",
        "number_of_page": "225",
        "isbn/asin": "",
        "download_link": "https://alvinalexander.com/scala/scala-book-free/"
    },
    {
        "title": "Notes on the Combinatorial Fundamentals of Algebra",
        "thumbnail_url": "http://www.e-booksdirectory.com/images/12412.jpg",
        "author": "Darij Grinberg",
        "publisher": "arXiv.org",
        "date_published": "2021",
        "number_of_page": "1359",
        "isbn/asin": "",
        "download_link": "https://arxiv.org/abs/2008.09862"
    },
    {
        "title": "Creative Multilingualism: A Manifesto",
        "thumbnail_url": "http://www.e-booksdirectory.com/imglrg/12411.jpg",
        "author": "Katrin Kohl, et al.",
        "publisher": "Open Book Publishers",
        "date_published": "",
        "number_of_page": "336",
        "isbn/asin": "9781783749317",
        "download_link": "https://www.openbookpublishers.com/product/1166"
    },
    {
        "title": "Africa South",
        "thumbnail_url": "http://www.e-booksdirectory.com/imglrg/12410.jpg",
        "author": "Harm J. de Blij",
        "publisher": "Northwestern University Press",
        "date_published": "1962",
        "number_of_page": "410",
        "isbn/asin": "9780810138278",
        "download_link": "https://doi.org/10.21985/N27X4H"
    },
    {
        "title": "The Story of Crime: From the Cradle to the Grave",
        "thumbnail_url": "http://www.e-booksdirectory.com/imglrg/12409.jpg",
        "author": "Hargrave Lee Adam",
        "publisher": "T. Werner Laurie",
        "date_published": "1908",
        "number_of_page": "462",
        "isbn/asin": "",
        "download_link": "https://archive.org/download/storyofcrimefrom00adamiala/storyofcrimefrom00adamiala.pdf"
    },
    {
        "title": "R-F Amplifiers",
        "thumbnail_url": "http://www.e-booksdirectory.com/images/12408.jpg",
        "author": "Alexander Schure",
        "publisher": "J. F. Rider",
        "date_published": "1959",
        "number_of_page": "102",
        "isbn/asin": "",
        "download_link": "https://worldradiohistory.com/BOOKSHELF-ARH/Rider-Books/R-F%20Amplifiers%20-%20Alexander%20Schure.pdf"
    }
]